tronpyweb/__init__.py
tronpyweb/main.py
tronpyweb-0.0.1.dist-info/LICENSE.txt
tronpyweb-0.0.1.dist-info/METADATA
tronpyweb-0.0.1.dist-info/WHEEL
tronpyweb-0.0.1.dist-info/top_level.txt
tronpyweb-0.0.1.dist-info/RECORD
