Metadata-Version: 2.1
Name: tronpyweb
Version: 0.0.1
Summary: tronpyweb library for Python
Author: johntron
Author-email: WilliamsMasinokyVSt@gmail.com
License: MIT
Project-URL: Source Repository, https://github.com/andelf/tronpy
License-File: LICENSE.txt
Requires-Dist: requests
